atom_encryption/__init__.py
atom_encryption/error_detection_tools.py
atom_encryption/irreversible_encryption_tools.py
atom_encryption/reversible_encryption_tools.py
atom_encryption/type_encode_decode_tools.py
atom_encryption-1.2.0.dist-info/LICENSE
atom_encryption-1.2.0.dist-info/METADATA
atom_encryption-1.2.0.dist-info/WHEEL
atom_encryption-1.2.0.dist-info/top_level.txt
atom_encryption-1.2.0.dist-info/RECORD
