Metadata-Version: 2.1
Name: atom-encryption
Version: 1.2.0
Summary: A Python library for reversible and irreversible encryption tools.
Home-page: https://github.com/alfredzhang98/atom_sdk/tree/master/atom_encryption
Author: alfred
Author-email: alfred.zhang98@gmail.com
License: MIT
Keywords: encryption,AES,RSA,ECC,cryptography,security
Classifier: Development Status :: 5 - Production/Stable
Classifier: Intended Audience :: Developers
Classifier: License :: OSI Approved :: MIT License
Classifier: Programming Language :: Python :: 3
Classifier: Programming Language :: Python :: 3.8
Classifier: Programming Language :: Python :: 3.9
Classifier: Programming Language :: Python :: 3.10
Requires-Python: >=3.8
License-File: LICENSE
Requires-Dist: cryptography
Requires-Dist: bcrypt
Requires-Dist: twofish
